[
  {
    "category": [
      "latina",
      "latino",
      "Latin America",
      "hispanic",
      "caramel"
    ],
    "entries": [
      "Spanish",
      "argentinian",
      "Cuban",
      "Colombian",
      "Puerto Rican",
      "Mexican",
      "Dominican",
      "Costa Rican",
      "Guatemalan",
      "Honduran",
      "Nicaraguan",
      "Panamanian",
      "Salvadoran",
      "Bolivian",
      "Chilean",
      "Ecuadorian",
      "Paraguayan",
      "Peruvian",
      "Uruguayan",
      "venezuelan"
    ]
  },
  {
    "category": [
      "asian",
      "asiatic"
    ],
    "entries": [
      "Laotian",
      "Surinamer",
      "Filipino",
      "Taiwanese",
      "Thai",
      "Indian",
      "Pakistani",
      "Bangladeshi",
      "Sri Lankan",
      "Nepalese",
      "Bhutanese",
      "Maldivian",
      "Japanese",
      "Chinese",
      "North Korean",
      "South Korean",
      "Mongolian",
      "Indonesian",
      "Malaysian",
      "Singaporean",
      "Bruneian",
      "Timor-Leste",
      "Timorese",
      "Burmese",
      "Lao",
      "Laotian",
      "Cambodian",
      "Vietnamese",
      "Kazakhstani",
      "Tajik",
      "Kyrgyz",
      "Uzbekistani",
      "Turkmenistani"
    ]
  },
  {
    "category": [
      "Middle East"
    ],
    "entries": [
      "Bosnian",
      "Turkish",
      "Saudi",
      "Omani",
      "Jordanian",
      "Qatari",
      "Kuwaiti",
      "Emiran",
      "Bahraini",
      "Armenian",
      "Azerbaijani",
      "Georgian",
      "Yemenite",
      "Iraqi",
      "Iranian",
      "Afghan",
      "Afghani",
      "Israeli",
      "Lebanese",
      "Palestinian",
      "Turkish",
      "Turks",
      "Cypriot",
      "Syrian"
    ]
  },
  {
    "category": [
      "Arabs"
    ],
    "entries": [
      "Bosnian",
      "Maltese",
      "Turkish",
      "Egyptian",
      "Algerian",
      "Sudanese",
      "Iraqi",
      "Moroccan",
      "Saudi",
      "Yemenite",
      "Syrian",
      "Tunisian",
      "Somali",
      "Jordanian",
      "Emirian",
      "Libyan",
      "Palestine",
      "Lebanese",
      "Omani",
      "Kuwaiti",
      "Mauritian",
      "Qatari",
      "Bahraini",
      "Djibouti",
      "Comoros"
    ]
  },
  {
    "category": [
      "African American",
      "Black American",
      "Negroid",
      "Negro",
      "Black",
      "chocolate"
    ],
    "entries": [
      "Batswana",
      "Mosotho",
      "Sao Tomean",
      "Motswana",
      "Central African",
      "Angolan",
      "Beninese",
      "Botswanans",
      "Burkinabe",
      "Faso",
      "Burundian",
      "Cameroonian",
      "Cape Verdean",
      "Chadian",
      "Comoran",
      "Congolese",
      "Cote",
      "Ivoire",
      "Ivorian",
      "Djibouti",
      "Equatorial Guinean",
      "Eritrean",
      "Ethiopian",
      "Gabonese",
      "Gambian",
      "Ghanaian",
      "Guinean",
      "Guinea-Bissauan",
      "Kenyan",
      "Lesotho",
      "Basotho",
      "Malawian",
      "Malian",
      "Mauritanian",
      "Mauritius",
      "Mozambican",
      "Namibian",
      "Nigerien",
      "Nigerian",
      "Rwandan",
      "Senegalese",
      "Seychellois",
      "Sierra Leonean",
      "Somali",
      "Motswana",
      "South African",
      "Sudanese",
      "Swazi",
      "Tanzanian",
      "Togolese",
      "Ugandan",
      "Zambian",
      "Zimbabwean"
    ]
  },
  {
    "category": [
      "Native Hawaiian",
      "Pacific Islander"
    ],
    "entries": [
      "East Timorese",
      "Papua New Guinean",
      "Fijian",
      "I-Kiribati",
      "Marshallese",
      "Micronesian",
      "Nauruan",
      "Palauan",
      "Samoan",
      "Solomon Islander",
      "Tongan",
      "Tuvaluan",
      "Ni-Vanuatu"
    ]
  },
  {
    "category": [
      "Native American",
      "Alaska Native"
    ],
    "entries": [
      "American Indians"
    ]
  },
  {
    "category": [
      "White",
      "European American",
      "Caucasian"
    ],
    "entries": [
      "Monacan",
      "San Marinese",
      "New Zealander",
      "Australian",
      "Andorran",
      "Luxembourger",
      "Liechtensteiner",
      "Moldovan",
      "Icelander",
      "Northern Irish",
      "Dutch",
      "Macedonian",
      "Maltese",
      "Herzegovinian",
      "Netherlander",
      "Danish",
      "British",
      "English",
      "Estonian",
      "Finnish",
      "Icelandic",
      "Irish",
      "Latvian",
      "Lithuanian",
      "Norwegian",
      "Scottish",
      "Swedish",
      "Dutchman",
      "Welsh",
      "Austrian",
      "Belgian",
      "French",
      "German",
      "Swiss",
      "Albanian",
      "Croatian",
      "Cypriot",
      "Greek",
      "Italian",
      "Portuguese",
      "Serbian",
      "Slovenian",
      "Spanish",
      "Belarusian",
      "Bulgarian",
      "Czech",
      "Hungarian",
      "Polish",
      "Romanian",
      "Russian",
      "Slovakian",
      "Ukrainian"
    ]
  },
  {
    "category": [
      "African"
    ],
    "entries": [
      "Batswana",
      "Mosotho",
      "Liberian",
      "Central African",
      "Algerian",
      "Egyptian",
      "Ghanaian",
      "Ivorian",
      "Libyan",
      "Moroccan",
      "Nigerian",
      "Tunisian",
      "Ethiopian",
      "Kenyan",
      "Somali",
      "Sudanese",
      "Tanzanian",
      "Ugandan",
      "Angolan",
      "Botswanan",
      "Congolese",
      "Malagasy",
      "Mozambican",
      "Namibian",
      "South African",
      "Zambian",
      "Zimbabwean"
    ]
  },
  {
    "category": [
      "caribbean"
    ],
    "entries": [
      "Anguillian",
      "Aruban",
      "Bahamian",
      "Barbadian",
      "Caymanian",
      "Cuban",
      "Curacao",
      "Dominica",
      "Grenedian",
      "Haitian",
      "Jamaican",
      "Puerto Rican",
      "Saint Lucian",
      "Trinidadian",
      "Trinbagonians",
      "Turks",
      "Caicos",
      "Kittian and Nevisian"
    ]
  },
  {
    "category": [
      "Mongoloid",
      "Mongolian"
    ],
    "entries": [
      "Mongol",
      "Chinese",
      "Indochinese",
      "Japanese",
      "Korean",
      "Tibetan",
      "Malay",
      "Polynesian",
      "Maori",
      "Micronesian",
      "Eskimo"
    ]
  }
]